setup.py
pypodio2/__init__.py
pypodio2/adapters.py
pypodio2/api.py
pypodio2/areas.py
pypodio2/client.py
pypodio2/encode.py
pypodio2/transport.py
pypodio2.egg-info/PKG-INFO
pypodio2.egg-info/SOURCES.txt
pypodio2.egg-info/dependency_links.txt
pypodio2.egg-info/requires.txt
pypodio2.egg-info/top_level.txt