Metadata-Version: 1.1
Name: pypodio2
Version: 0.1
Summary: Python wrapper for the Podio API
Home-page: https://github.com/podio/podio-py
Author: Podio
Author-email: mail@podio.com
License: MIT
Platform: UNKNOWN
Classifier: Development Status :: 4 - Beta
Classifier: Intended Audience :: Developers
Classifier: Operating System :: OS Independent
Classifier: Programming Language :: Python
Classifier: License :: OSI Approved :: MIT License
Classifier: Topic :: Software Development :: Libraries :: Python Modules
